ALU.v
module ALU(
	input wire [7:0] A,
	input wire [7:0] B,
	input wire [3:0] op,	//功能码，选择运算类型(预留4位，实际1位就行)
	output wire [7:0] E,
	output wire [1:0] cc	//编码两个操作数，左边用于标识AB是否相等，相等的话为1.
							//右边用于标识A是否大于B，1表示A大于B，0表示A小于B

);
	assign E = ( op == 4'h0 )? A+B :
		   		(op == 4'h1) ? A-B : 8'hxx;
		   		
	assign cc =  {A==B,A>B} 	;  //拼接运算符

endmodule

//OP=0000 加法 A+B
//OP=0001 减法 A-B
//否则：不定值，以后扩充运算符

REGFILE.v
module REGFILE(
	input wire [2:0] srcA,
	input wire [2:0] srcB,
	output wire [7:0] A,
	output wire [7:0] B,
	input wire [2:0] dstM,
	input wire [2:0] dstE,
	input wire [7:0] M,			
	input wire [7:0] E,
	input wire clk	
);

	reg [7:0] rf [0:7];
	assign A = (srcA==3'b000)? 8'h00 : rf[srcA];  //如果srcA是0必须返回一个零值	
	assign B = (srcB==3'o0)? 8'h00 : rf[srcB]; //同上
	
	always @(posedge clk) 
    begin
		if(dstM!=3'o0) 
            rf[dstM] <= M;					
		if(dstE!=3'o0 && dstE!=dstM)  //如果两个地址是同一个地址，需要有一个优先级(POP指令会涉及)，令M端口优先(栈顶的值存入EXP中)
            rf[dstE] <= E;		
	end
endmodule

PC.v
//用于给出指令在指令储存器中的地址
//在时钟信号的上升沿更新，而且需要一个控制信号，在控制信号为0的时候初始化PC寄存器
module PC(
	input wire [7:0] new_pc,  //目标地址，可能是跳转地址或者是下一条指令的地址
	output reg [7:0] pc, //指令地址，输出信号
	input wire clk,  //时钟周期
	input wire rst_  
);
	always @(posedge clk or negedge rst_) 
	begin
		if(rst_==1'b0)
			begin
			pc<=0;
			end
	 	else    //返回指令地址
			begin
			pc<=new_pc;
			end
	end
		
endmodule

TINYCPU.v
`include "tinyCPU.h"

`define ins rom_data[23:20]   	// -> icode (ROM中高四位)
`define fun rom_data[19:16]		// -> ifun (ROM中低四位)，功能码
`define rA  rom_data[14:12]		//只用3位来表示Ra（一共8个寄存器，3位寻址）
`define rB  rom_data[10:8]    //只用3位
`define rC 	rom_data[6:4]		//第三个字节高四位的低三位用来表示rC

module TINYCPU(
	//连接RAM端口
	output wire [7:0] ram_addr,  //写RAM地址
	output wire [7:0] ram_wdat,  //向RAM写数据总线
	input wire [7:0] ram_rdat,  //读总线
	output wire ram_rd_,ram_wr_,  //控制信号
	
	//连接ROM端口
	output wire [7:0] rom_addr,
	input wire [23:0] rom_data,
	
	//时钟信号与复位信号(CPU复位->PC寄存器置0，从0取出第一条地址)
	input wire clk,rst_
);

	wire [7:0] valA,valB,valC,valP,valE,valM,aluB,new_pc;
	wire [1:0] cc;
	wire [2:0] dstE, dstM;
	
	PC pc( .new_pc(new_pc),.pc(rom_addr),.clk(clk),.rst_(rst_)); //实例化一个PC寄存器
	
	assign valC = (`ins==`JXX && `fun==`JMP) ? rom_data[15:8] : rom_data[7:0];  //如果取出来了一个无条件转移指令，输出第二个字节，否则其他的是第三个字节
	
	assign valP = rom_addr + ((`ins==`HLT )? 0:
						 (`ins==`NOP )? 1: 
						 (`ins==`JXX && `fun==`JMP) ? 2:3);  //下一条指令的地址
	
	REGFILE regfile(.srcA(`rA),.srcB(`rB),.A(valA),.B(valB),.dstM(dstM),.dstE(dstE),.M(valM),.E(valE),.clk(clk)	);  //实例化译码器，虽然全部读出来了但是不一定全都用，这样可以简化电路
	
	assign aluB= (`ins==`LD||`ins==`ST||`ins==`OPI)?valC:valB;			//状态信号
	
	ALU alu(.A(valA),.B(aluB),.op(`fun),.E(valE),.cc(cc));   //实例化一个运算器
	//访存阶段:
	assign ram_addr=valE; //地址就是运算器输出的结果
	assign ram_wdat=valB;  
	assign valM=ram_rdat;  //从RAM读出来的值写到valM端口
	assign ram_rd_ = (`ins==`LD) ? 1'b0 : 1'b1;				//LD命令，rd_信号有效
	assign ram_wr_ = (`ins==`ST) ? 1'b0 : 1'b1;	 
	//写回阶段:
	assign dstM = (`ins==`LD) ? `rB : 3'o0; //代替写使能信号，不是LD的话全写0，表示不写入寄存器
	assign dstE = (`ins==`OPR) ? `rC :
				  (`ins==`OPI) ? `rB : 3'o0;
				  //其他指令不应该修改寄存器内容		  
	assign new_pc= (
					(`ins == `JXX && `fun == `JMP)||
					(`ins == `JXX && `fun == `BEQ &&  cc[1:1])||
					(`ins == `JXX && `fun == `BNE && ~cc[1:1])||
					(`ins == `JXX && `fun == `BLT && ~cc[1:1] && ~cc[0:0])||
					(`ins == `JXX && `fun == `BGT && ~cc[1:1] &&  cc[0:0]))? valC :valP;
					//如果成功转移则为valC,不转移则为下一条指令valP
			
endmodule

ROM.v
module ROM(
	input wire [7:0] addr,   //8位地址输入
	output wire [23 :0] out   //需要输出一整条指令，需要三个字节24位
);

	reg [7:0] mem [0:255];  //存储单元
	
	assign out = {mem[addr],mem[addr+1],mem[addr+2]};   //连续输出三个字节
	
	initial
		$readmemh("rom.txt",mem,0,255); //利用系统任务读入
	
endmodule

RAM.v
module RAM(
	input wire [7:0] addr,   //地址总线
	input wire [7:0] in,  //数据总线
	output wire [7:0] out,   //数据输出
	input wire rd_, //控制读信号(低电平有效)
	input wire wr_, //控制写信号(低电平有效)
	input wire clk
);
	reg [7:0] mem [0:255];   //存储单元，共256个，每一个8位
		
	assign out = (rd_==1'b0)? mem[addr] : 8'hxx;	//读数据

	always @(posedge clk) 
		if(wr_==1'b0)  //写信号有效时写入数据
			mem[addr] <= in;  //线网型尽可能连续赋值

endmodule

test.v
`timescale 10ns/1ns

`include "tinyCPU.h"

`define ins rom_out [23:20]

module test;
	wire [7:0] ram_addr, ram_in ,ram_out, rom_addr;
	wire [23:0] rom_out;
	wire rd_,wr_;
	reg clk,rst_;
	
	parameter CYCLE =1.0;
	
	RAM ram(.addr(ram_addr),.in(ram_in),.out(ram_out),.rd_(rd_),.wr_(wr_),.clk(clk));
	ROM rom(.addr(rom_addr),.out(rom_out));
	
	TINYCPU cpu (.ram_addr(ram_addr),.ram_wdat(ram_in),.ram_rdat(ram_out),.ram_rd_(rd_),.ram_wr_(wr_),
				.rom_addr(rom_addr),.rom_data(rom_out),
				.clk(clk),.rst_(rst_));
				
	always #(CYCLE/2)  clk <= ~clk;  //产生时钟
	
	integer i;

	//每到时钟的下降沿(时钟周期的中间时刻)，把内存中前32位的值输出一遍:
	always @(negedge clk) begin
		if (rst_&&(`ins==`HLT)) #(CYCLE+0.1) $finish; //结束当前仿真
		$write("%3d: ",$stime); //显示出仿真时间
		for(i=0;i<32;i=i+1)
			if(ram.mem[i]!==8'hxx) $write(" %c ",ram.mem[i]); 
			else $write(" .  ");  //如果是不确定值，输出一个·
		$write("\n"); 
		end
	
	initial begin    
		$dumpfile("test.vcd");
		$dumpvars;
		$readmemh("ram.txt",ram.mem,0,255);   //16进制
		$readmemh("rom.txt",rom.mem,0,255);   //16进制
		clk=1'b1; 
		rst_=1'b0; #(CYCLE+CYCLE/2) rst_= ~rst_;  //初始reset为0，一个半时钟周期后reset结束
		end

endmodule

test.vcd
$date
	Mon May 31 22:55:39 2021
$end
$version
	Icarus Verilog
$end
$timescale
	1ns
$end
$scope module test $end
$var wire 1 ! wr_ $end
$var wire 24 " rom_out [23:0] $end
$var wire 8 # rom_addr [7:0] $end
$var wire 1 $ rd_ $end
$var wire 8 % ram_out [7:0] $end
$var wire 8 & ram_in [7:0] $end
$var wire 8 ' ram_addr [7:0] $end
$var reg 1 ( clk $end
$var reg 1 ) rst_ $end
$var integer 32 * i [31:0] $end
$scope module cpu $end
$var wire 1 ( clk $end
$var wire 8 + ram_addr [7:0] $end
$var wire 8 , ram_wdat [7:0] $end
$var wire 1 ) rst_ $end
$var wire 8 - valM [7:0] $end
$var wire 8 . valP [7:0] $end
$var wire 8 / valE [7:0] $end
$var wire 8 0 valC [7:0] $end
$var wire 8 1 valB [7:0] $end
$var wire 8 2 valA [7:0] $end
$var wire 24 3 rom_data [23:0] $end
$var wire 8 4 rom_addr [7:0] $end
$var wire 1 ! ram_wr_ $end
$var wire 8 5 ram_rdat [7:0] $end
$var wire 1 $ ram_rd_ $end
$var wire 8 6 new_pc [7:0] $end
$var wire 3 7 dstM [2:0] $end
$var wire 3 8 dstE [2:0] $end
$var wire 2 9 cc [1:0] $end
$var wire 8 : aluB [7:0] $end
$scope module alu $end
$var wire 8 ; B [7:0] $end
$var wire 4 < op [3:0] $end
$var wire 2 = cc [1:0] $end
$var wire 8 > E [7:0] $end
$var wire 8 ? A [7:0] $end
$upscope $end
$scope module pc $end
$var wire 1 ( clk $end
$var wire 8 @ new_pc [7:0] $end
$var wire 1 ) rst_ $end
$var reg 8 A pc [7:0] $end
$upscope $end
$scope module regfile $end
$var wire 8 B E [7:0] $end
$var wire 8 C M [7:0] $end
$var wire 1 ( clk $end
$var wire 3 D dstE [2:0] $end
$var wire 3 E dstM [2:0] $end
$var wire 3 F srcA [2:0] $end
$var wire 3 G srcB [2:0] $end
$var wire 8 H B [7:0] $end
$var wire 8 I A [7:0] $end
$upscope $end
$upscope $end
$scope module ram $end
$var wire 8 J addr [7:0] $end
$var wire 1 ( clk $end
$var wire 8 K in [7:0] $end
$var wire 1 $ rd_ $end
$var wire 1 ! wr_ $end
$var wire 8 L out [7:0] $end
$upscope $end
$scope module rom $end
$var wire 8 M addr [7:0] $end
$var wire 24 N out [23:0] $end
$upscope $end
$upscope $end
$enddefinitions $end
#0
$dumpvars
b10000000000000100000000 N
b0 M
bx L
bx K
b0 J
b0 I
bx H
b1 G
b0 F
b0 E
b1 D
bx C
b0 B
b0 A
b11 @
b0 ?
b0 >
b10 =
b0 <
b0 ;
b0 :
b10 9
b1 8
b0 7
b11 6
bx 5
b0 4
b10000000000000100000000 3
b0 2
bx 1
b0 0
b0 /
b11 .
bx -
bx ,
b0 +
bx *
0)
1(
b0 '
bx &
bx %
1$
b0 #
b10000000000000100000000 "
1!
$end
#5
b100000 *
0(
#10
b0 &
b0 ,
b0 K
b0 1
b0 H
1(
#15
b100000 *
0(
1)
#20
b1000001 -
b1000001 C
b1000001 %
b1000001 5
b1000001 L
b0 8
b0 D
b10 7
b10 E
0$
bx &
bx ,
bx K
bx 1
bx H
b10 G
b1 F
b110 6
b110 @
b100000001001000000000 "
b100000001001000000000 3
b100000001001000000000 N
b110 .
b11 #
b11 4
b11 A
b11 M
1(
#25
b100000 *
0(
#30
bx -
bx C
bx %
bx 5
bx L
b0 :
b0 ;
1$
bx '
bx +
bx J
bx /
bx >
bx B
b0 7
b0 E
b1 9
b1 =
b1000001 2
b1000001 ?
b1000001 I
b1010 0
b10 <
b0 G
b10 F
b1010 6
b1010 @
b0 &
b0 ,
b0 K
b0 1
b0 H
b10100100010000000001010 "
b10100100010000000001010 3
b10100100010000000001010 N
b1001 .
b110 #
b110 4
b110 A
b110 M
1(
#35
b100000 *
0(
#40
b11 8
b11 D
b1000001 :
b1000001 ;
b1101 6
b1101 @
b1000001 '
b1000001 +
b1000001 J
b1000001 /
b1000001 >
b1000001 B
bx &
bx ,
bx K
bx 1
bx H
b0 9
b0 =
b0 2
b0 ?
b0 I
b1000001 0
b0 <
b11 G
b0 F
b10000000000001101000001 "
b10000000000001101000001 3
b10000000000001101000001 N
b1101 .
b1010 #
b1010 4
b1010 A
b1010 M
1(
#45
b100000 *
0(
#50
b0 8
b0 D
bx '
bx +
bx J
bx /
bx >
bx B
b10 9
b10 =
b1000001 2
b1000001 ?
b1000001 I
b110000 0
b11 <
b10 F
b10000 6
b10000 @
b1000001 &
b1000001 ,
b1000001 K
b1000001 1
b1000001 H
b10100110010001100110000 "
b10100110010001100110000 3
b10100110010001100110000 N
b10000 .
b1101 #
b1101 4
b1101 A
b1101 M
1(
#55
b100000 *
0(
#60
b11 8
b11 D
b1111010 :
b1111010 ;
b1111010 '
b1111010 +
b1111010 J
b1111010 /
b1111010 >
b1111010 B
b0 9
b0 =
b0 2
b0 ?
b0 I
b1111010 0
b0 <
b0 F
b10011 6
b10011 @
b10000000000001101111010 "
b10000000000001101111010 3
b10000000000001101111010 N
b10011 .
b10000 #
b10000 4
b10000 A
b10000 M
1(
#65
b100000 *
0(
#70
b0 8
b0 D
bx '
bx +
bx J
bx /
bx >
bx B
b1000001 2
b1000001 ?
b1000001 I
b110000 0
b100 <
b10 F
b10110 6
b10110 @
b1111010 &
b1111010 ,
b1111010 K
b1111010 1
b1111010 H
b10101000010001100110000 "
b10101000010001100110000 3
b10101000010001100110000 N
b10110 .
b10011 #
b10011 4
b10011 A
b10011 M
1(
#75
b100000 *
0(
#80
b11 8
b11 D
b1011010 :
b1011010 ;
b1011010 '
b1011010 +
b1011010 J
b1011010 /
b1011010 >
b1011010 B
b0 2
b0 ?
b0 I
b1011010 0
b0 <
b0 F
b11001 6
b11001 @
b10000000000001101011010 "
b10000000000001101011010 3
b10000000000001101011010 N
b11001 .
b10110 #
b10110 4
b10110 A
b10110 M
1(
#85
b100000 *
0(
#90
b0 8
b0 D
bx '
bx +
bx J
bx /
bx >
bx B
b1000001 2
b1000001 ?
b1000001 I
b100100 0
b100 <
b10 F
b11100 6
b11100 @
b1011010 &
b1011010 ,
b1011010 K
b1011010 1
b1011010 H
b10101000010001100100100 "
b10101000010001100100100 3
b10101000010001100100100 N
b11100 .
b11001 #
b11001 4
b11001 A
b11001 M
1(
#95
b100000 *
0(
#100
b10 8
b10 D
b1 9
b1 =
b100000 :
b100000 ;
b1100001 '
b1100001 +
b1100001 J
b1100001 /
b1100001 >
b1100001 B
b1000001 &
b1000001 ,
b1000001 K
b1000001 1
b1000001 H
b100000 0
b0 <
b10 G
b11111 6
b11111 @
b10000000010001000100000 "
b10000000010001000100000 3
b10000000010001000100000 N
b11111 .
b11100 #
b11100 4
b11100 A
b11100 M
1(
#105
b100000 *
0(
#110
b0 8
b0 D
b0 :
b0 ;
0!
b10 9
b10 =
b0 0
b0 '
b0 +
b0 J
b0 /
b0 >
b0 B
b1 F
b100010 6
b100010 @
b0 2
b0 ?
b0 I
b1100001 &
b1100001 ,
b1100001 K
b1100001 1
b1100001 H
b1000000001001000000000 "
b1000000001001000000000 3
b1000000001001000000000 N
b100010 .
b11111 #
b11111 4
b11111 A
b11111 M
1(
#115
b100000 *
0(
#120
b1011010 '
b1011010 +
b1011010 J
b1011010 /
b1011010 >
b1011010 B
b0 :
b0 ;
1!
b0 &
b0 ,
b0 K
b0 1
b0 H
b1 9
b1 =
b1011010 2
b1011010 ?
b1011010 I
b110000 0
b0 G
b11 F
b110000 6
b110000 @
b10100000011000001000000 "
b10100000011000001000000 3
b10100000011000001000000 N
b100100 .
b100010 #
b100010 4
b100010 A
b100010 M
1(
#125
b100000 *
0(
#130
b1 8
b1 D
b1 :
b1 ;
b1 '
b1 +
b1 J
b1 /
b1 >
b1 B
b110011 6
b110011 @
b0 9
b0 =
b0 2
b0 ?
b0 I
b1 0
b1 G
b1 F
b10000000001000100000001 "
b10000000001000100000001 3
b10000000001000100000001 N
b110011 .
b110000 #
b110000 4
b110000 A
b110000 M
1(
#135
b100000 *
0(
#140
b0 8
b0 D
b1011010 :
b1011010 ;
b11 0
b1011010 '
b1011010 +
b1011010 J
b1011010 /
b1011010 >
b1011010 B
b11 G
b0 F
b11 6
b11 @
b0 9
b0 =
b0 2
b0 ?
b0 I
b1011010 &
b1011010 ,
b1011010 K
b1011010 1
b1011010 H
b101000000000011xxxxxxxx "
b101000000000011xxxxxxxx 3
b101000000000011xxxxxxxx N
b110101 .
b110011 #
b110011 4
b110011 A
b110011 M
1(
#145
b100000 *
0(
#150
b110000 -
b110000 C
b110000 %
b110000 5
b110000 L
b1 9
b1 =
b0 :
b0 ;
b1 '
b1 +
b1 J
b1 /
b1 >
b1 B
b110 6
b110 @
b10 7
b10 E
0$
b1100001 &
b1100001 ,
b1100001 K
b1100001 1
b1100001 H
b1 2
b1 ?
b1 I
b0 0
b10 G
b1 F
b100000001001000000000 "
b100000001001000000000 3
b100000001001000000000 N
b110 .
b11 #
b11 4
b11 A
b11 M
1(
#155
b100000 *
0(
#160
bx -
bx C
bx %
bx 5
bx L
b0 :
b0 ;
1$
bx '
bx +
bx J
bx /
bx >
bx B
b0 7
b0 E
b110000 2
b110000 ?
b110000 I
b1010 0
b10 <
b0 G
b10 F
b1010 6
b1010 @
b0 &
b0 ,
b0 K
b0 1
b0 H
b10100100010000000001010 "
b10100100010000000001010 3
b10100100010000000001010 N
b1001 .
b110 #
b110 4
b110 A
b110 M
1(
#165
b100000 *
0(
#170
b11 8
b11 D
b1000001 :
b1000001 ;
b1101 6
b1101 @
b1000001 '
b1000001 +
b1000001 J
b1000001 /
b1000001 >
b1000001 B
b1011010 &
b1011010 ,
b1011010 K
b1011010 1
b1011010 H
b0 9
b0 =
b0 2
b0 ?
b0 I
b1000001 0
b0 <
b11 G
b0 F
b10000000000001101000001 "
b10000000000001101000001 3
b10000000000001101000001 N
b1101 .
b1010 #
b1010 4
b1010 A
b1010 M
1(
#175
b100000 *
0(
#180
b0 8
b0 D
bx '
bx +
bx J
bx /
bx >
bx B
b110000 2
b110000 ?
b110000 I
b110000 0
b11 <
b10 F
b110000 6
b110000 @
b1000001 &
b1000001 ,
b1000001 K
b1000001 1
b1000001 H
b10100110010001100110000 "
b10100110010001100110000 3
b10100110010001100110000 N
b10000 .
b1101 #
b1101 4
b1101 A
b1101 M
1(
#185
b100000 *
0(
#190
b1 8
b1 D
b10 9
b10 =
b1 :
b1 ;
b110011 6
b110011 @
b10 '
b10 +
b10 J
b10 /
b10 >
b10 B
b1 &
b1 ,
b1 K
b1 1
b1 H
b1 2
b1 ?
b1 I
b1 0
b0 <
b1 G
b1 F
b10000000001000100000001 "
b10000000001000100000001 3
b10000000001000100000001 N
b110011 .
b110000 #
b110000 4
b110000 A
b110000 M
1(
#195
b100000 *
0(
#200
b0 8
b0 D
b1000001 :
b1000001 ;
b11 0
b1000001 '
b1000001 +
b1000001 J
b1000001 /
b1000001 >
b1000001 B
b11 G
b0 F
b11 6
b11 @
b0 9
b0 =
b0 2
b0 ?
b0 I
b1000001 &
b1000001 ,
b1000001 K
b1000001 1
b1000001 H
b101000000000011xxxxxxxx "
b101000000000011xxxxxxxx 3
b101000000000011xxxxxxxx N
b110101 .
b110011 #
b110011 4
b110011 A
b110011 M
1(
#205
b100000 *
0(
#210
b1100001 -
b1100001 C
b1100001 %
b1100001 5
b1100001 L
b1 9
b1 =
b0 :
b0 ;
b10 '
b10 +
b10 J
b10 /
b10 >
b10 B
b110 6
b110 @
b10 7
b10 E
0$
b110000 &
b110000 ,
b110000 K
b110000 1
b110000 H
b10 2
b10 ?
b10 I
b0 0
b10 G
b1 F
b100000001001000000000 "
b100000001001000000000 3
b100000001001000000000 N
b110 .
b11 #
b11 4
b11 A
b11 M
1(
#215
b100000 *
0(
#220
bx -
bx C
bx %
bx 5
bx L
b0 :
b0 ;
1$
bx '
bx +
bx J
bx /
bx >
bx B
b0 7
b0 E
b1100001 2
b1100001 ?
b1100001 I
b1010 0
b10 <
b0 G
b10 F
b1010 6
b1010 @
b0 &
b0 ,
b0 K
b0 1
b0 H
b10100100010000000001010 "
b10100100010000000001010 3
b10100100010000000001010 N
b1001 .
b110 #
b110 4
b110 A
b110 M
1(
#225
b100000 *
0(
#230
b11 8
b11 D
b1000001 :
b1000001 ;
b1101 6
b1101 @
b1000001 '
b1000001 +
b1000001 J
b1000001 /
b1000001 >
b1000001 B
b1000001 &
b1000001 ,
b1000001 K
b1000001 1
b1000001 H
b0 9
b0 =
b0 2
b0 ?
b0 I
b1000001 0
b0 <
b11 G
b0 F
b10000000000001101000001 "
b10000000000001101000001 3
b10000000000001101000001 N
b1101 .
b1010 #
b1010 4
b1010 A
b1010 M
1(
#235
b100000 *
0(
#240
b0 8
b0 D
bx '
bx +
bx J
bx /
bx >
bx B
b1 9
b1 =
b1100001 2
b1100001 ?
b1100001 I
b110000 0
b11 <
b10 F
b10000 6
b10000 @
b10100110010001100110000 "
b10100110010001100110000 3
b10100110010001100110000 N
b10000 .
b1101 #
b1101 4
b1101 A
b1101 M
1(
#245
b100000 *
0(
#250
b11 8
b11 D
b1111010 :
b1111010 ;
b1111010 '
b1111010 +
b1111010 J
b1111010 /
b1111010 >
b1111010 B
b0 9
b0 =
b0 2
b0 ?
b0 I
b1111010 0
b0 <
b0 F
b10011 6
b10011 @
b10000000000001101111010 "
b10000000000001101111010 3
b10000000000001101111010 N
b10011 .
b10000 #
b10000 4
b10000 A
b10000 M
1(
#255
b100000 *
0(
#260
b0 8
b0 D
bx '
bx +
bx J
bx /
bx >
bx B
b1100001 2
b1100001 ?
b1100001 I
b110000 0
b100 <
b10 F
b10110 6
b10110 @
b1111010 &
b1111010 ,
b1111010 K
b1111010 1
b1111010 H
b10101000010001100110000 "
b10101000010001100110000 3
b10101000010001100110000 N
b10110 .
b10011 #
b10011 4
b10011 A
b10011 M
1(
#265
b100000 *
0(
#270
b11 8
b11 D
b1011010 :
b1011010 ;
b1011010 '
b1011010 +
b1011010 J
b1011010 /
b1011010 >
b1011010 B
b0 2
b0 ?
b0 I
b1011010 0
b0 <
b0 F
b11001 6
b11001 @
b10000000000001101011010 "
b10000000000001101011010 3
b10000000000001101011010 N
b11001 .
b10110 #
b10110 4
b10110 A
b10110 M
1(
#275
b100000 *
0(
#280
b0 8
b0 D
bx '
bx +
bx J
bx /
bx >
bx B
b1 9
b1 =
b1100001 2
b1100001 ?
b1100001 I
b100100 0
b100 <
b10 F
b100100 6
b100100 @
b1011010 &
b1011010 ,
b1011010 K
b1011010 1
b1011010 H
b10101000010001100100100 "
b10101000010001100100100 3
b10101000010001100100100 N
b11100 .
b11001 #
b11001 4
b11001 A
b11001 M
1(
#285
b100000 *
0(
#290
b11 8
b11 D
b1100001 :
b1100001 ;
b100111 6
b100111 @
b1100001 '
b1100001 +
b1100001 J
b1100001 /
b1100001 >
b1100001 B
b0 9
b0 =
b0 2
b0 ?
b0 I
b1100001 0
b0 <
b0 F
b10000000000001101100001 "
b10000000000001101100001 3
b10000000000001101100001 N
b100111 .
b100100 #
b100100 4
b100100 A
b100100 M
1(
#295
b100000 *
0(
#300
b0 8
b0 D
bx '
bx +
bx J
bx /
bx >
bx B
b10 9
b10 =
b1100001 2
b1100001 ?
b1100001 I
b110000 0
b11 <
b10 F
b101010 6
b101010 @
b1100001 &
b1100001 ,
b1100001 K
b1100001 1
b1100001 H
b10100110010001100110000 "
b10100110010001100110000 3
b10100110010001100110000 N
b101010 .
b100111 #
b100111 4
b100111 A
b100111 M
1(
#305
b100000 *
0(
#310
b10 8
b10 D
b1000001 '
b1000001 +
b1000001 J
b1000001 /
b1000001 >
b1000001 B
b1 9
b1 =
b100000 :
b100000 ;
b100000 0
b1 <
b10 G
b101101 6
b101101 @
b10000010010001000100000 "
b10000010010001000100000 3
b10000010010001000100000 N
b101101 .
b101010 #
b101010 4
b101010 A
b101010 M
1(
#315
b100000 *
0(
#320
b0 8
b0 D
b0 :
b0 ;
0!
b10 '
b10 +
b10 J
b10 /
b10 >
b10 B
b1 9
b1 =
b0 0
b0 <
b1 F
b110000 6
b110000 @
b10 2
b10 ?
b10 I
b1000001 &
b1000001 ,
b1000001 K
b1000001 1
b1000001 H
b1000000001001000000000 "
b1000000001001000000000 3
b1000000001001000000000 N
b110000 .
b101101 #
b101101 4
b101101 A
b101101 M
1(
#325
b100000 *
0(
#330
b11 '
b11 +
b11 J
b11 /
b11 >
b11 B
b1 8
b1 D
b1 :
b1 ;
1!
b10 &
b10 ,
b10 K
b10 1
b10 H
b1 0
b1 G
b110011 6
b110011 @
b10000000001000100000001 "
b10000000001000100000001 3
b10000000001000100000001 N
b110011 .
b110000 #
b110000 4
b110000 A
b110000 M
1(
#335
b100000 *
0(
#340
b0 8
b0 D
b1100001 :
b1100001 ;
b0 9
b0 =
b11 0
b1100001 '
b1100001 +
b1100001 J
b1100001 /
b1100001 >
b1100001 B
b11 G
b0 F
b11 6
b11 @
b0 2
b0 ?
b0 I
b1100001 &
b1100001 ,
b1100001 K
b1100001 1
b1100001 H
b101000000000011xxxxxxxx "
b101000000000011xxxxxxxx 3
b101000000000011xxxxxxxx N
b110101 .
b110011 #
b110011 4
b110011 A
b110011 M
1(
#345
b100000 *
0(
#350
b110001 -
b110001 C
b110001 %
b110001 5
b110001 L
b1 9
b1 =
b0 :
b0 ;
b11 '
b11 +
b11 J
b11 /
b11 >
b11 B
b110 6
b110 @
b10 7
b10 E
0$
b1000001 &
b1000001 ,
b1000001 K
b1000001 1
b1000001 H
b11 2
b11 ?
b11 I
b0 0
b10 G
b1 F
b100000001001000000000 "
b100000001001000000000 3
b100000001001000000000 N
b110 .
b11 #
b11 4
b11 A
b11 M
1(
#355
b100000 *
0(
#360
bx -
bx C
bx %
bx 5
bx L
b0 :
b0 ;
1$
bx '
bx +
bx J
bx /
bx >
bx B
b0 7
b0 E
b110001 2
b110001 ?
b110001 I
b1010 0
b10 <
b0 G
b10 F
b1010 6
b1010 @
b0 &
b0 ,
b0 K
b0 1
b0 H
b10100100010000000001010 "
b10100100010000000001010 3
b10100100010000000001010 N
b1001 .
b110 #
b110 4
b110 A
b110 M
1(
#365
b100000 *
0(
#370
b11 8
b11 D
b1000001 :
b1000001 ;
b1101 6
b1101 @
b1000001 '
b1000001 +
b1000001 J
b1000001 /
b1000001 >
b1000001 B
b1100001 &
b1100001 ,
b1100001 K
b1100001 1
b1100001 H
b0 9
b0 =
b0 2
b0 ?
b0 I
b1000001 0
b0 <
b11 G
b0 F
b10000000000001101000001 "
b10000000000001101000001 3
b10000000000001101000001 N
b1101 .
b1010 #
b1010 4
b1010 A
b1010 M
1(
#375
b100000 *
0(
#380
b0 8
b0 D
bx '
bx +
bx J
bx /
bx >
bx B
b110001 2
b110001 ?
b110001 I
b110000 0
b11 <
b10 F
b110000 6
b110000 @
b1000001 &
b1000001 ,
b1000001 K
b1000001 1
b1000001 H
b10100110010001100110000 "
b10100110010001100110000 3
b10100110010001100110000 N
b10000 .
b1101 #
b1101 4
b1101 A
b1101 M
1(
#385
b100000 *
0(
#390
b1 8
b1 D
b1 9
b1 =
b1 :
b1 ;
b110011 6
b110011 @
b100 '
b100 +
b100 J
b100 /
b100 >
b100 B
b11 &
b11 ,
b11 K
b11 1
b11 H
b11 2
b11 ?
b11 I
b1 0
b0 <
b1 G
b1 F
b10000000001000100000001 "
b10000000001000100000001 3
b10000000001000100000001 N
b110011 .
b110000 #
b110000 4
b110000 A
b110000 M
1(
#395
b100000 *
0(
#400
b0 8
b0 D
b1000001 :
b1000001 ;
b0 9
b0 =
b11 0
b1000001 '
b1000001 +
b1000001 J
b1000001 /
b1000001 >
b1000001 B
b11 G
b0 F
b11 6
b11 @
b0 2
b0 ?
b0 I
b1000001 &
b1000001 ,
b1000001 K
b1000001 1
b1000001 H
b101000000000011xxxxxxxx "
b101000000000011xxxxxxxx 3
b101000000000011xxxxxxxx N
b110101 .
b110011 #
b110011 4
b110011 A
b110011 M
1(
#405
b100000 *
0(
#410
b1000010 -
b1000010 C
b1000010 %
b1000010 5
b1000010 L
b1 9
b1 =
b0 :
b0 ;
b100 '
b100 +
b100 J
b100 /
b100 >
b100 B
b110 6
b110 @
b10 7
b10 E
0$
b110001 &
b110001 ,
b110001 K
b110001 1
b110001 H
b100 2
b100 ?
b100 I
b0 0
b10 G
b1 F
b100000001001000000000 "
b100000001001000000000 3
b100000001001000000000 N
b110 .
b11 #
b11 4
b11 A
b11 M
1(
#415
b100000 *
0(
#420
bx -
bx C
bx %
bx 5
bx L
b0 :
b0 ;
1$
bx '
bx +
bx J
bx /
bx >
bx B
b0 7
b0 E
b1000010 2
b1000010 ?
b1000010 I
b1010 0
b10 <
b0 G
b10 F
b1010 6
b1010 @
b0 &
b0 ,
b0 K
b0 1
b0 H
b10100100010000000001010 "
b10100100010000000001010 3
b10100100010000000001010 N
b1001 .
b110 #
b110 4
b110 A
b110 M
1(
#425
b100000 *
0(
#430
b11 8
b11 D
b1000001 :
b1000001 ;
b1101 6
b1101 @
b1000001 '
b1000001 +
b1000001 J
b1000001 /
b1000001 >
b1000001 B
b1000001 &
b1000001 ,
b1000001 K
b1000001 1
b1000001 H
b0 9
b0 =
b0 2
b0 ?
b0 I
b1000001 0
b0 <
b11 G
b0 F
b10000000000001101000001 "
b10000000000001101000001 3
b10000000000001101000001 N
b1101 .
b1010 #
b1010 4
b1010 A
b1010 M
1(
#435
b100000 *
0(
#440
b0 8
b0 D
bx '
bx +
bx J
bx /
bx >
bx B
b1 9
b1 =
b1000010 2
b1000010 ?
b1000010 I
b110000 0
b11 <
b10 F
b10000 6
b10000 @
b10100110010001100110000 "
b10100110010001100110000 3
b10100110010001100110000 N
b10000 .
b1101 #
b1101 4
b1101 A
b1101 M
1(
#445
b100000 *
0(
#450
b11 8
b11 D
b1111010 :
b1111010 ;
b1111010 '
b1111010 +
b1111010 J
b1111010 /
b1111010 >
b1111010 B
b0 9
b0 =
b0 2
b0 ?
b0 I
b1111010 0
b0 <
b0 F
b10011 6
b10011 @
b10000000000001101111010 "
b10000000000001101111010 3
b10000000000001101111010 N
b10011 .
b10000 #
b10000 4
b10000 A
b10000 M
1(
#455
b100000 *
0(
#460
b0 8
b0 D
bx '
bx +
bx J
bx /
bx >
bx B
b1000010 2
b1000010 ?
b1000010 I
b110000 0
b100 <
b10 F
b10110 6
b10110 @
b1111010 &
b1111010 ,
b1111010 K
b1111010 1
b1111010 H
b10101000010001100110000 "
b10101000010001100110000 3
b10101000010001100110000 N
b10110 .
b10011 #
b10011 4
b10011 A
b10011 M
1(
#465
b100000 *
0(
