ALU.v
module ALU(
	input wire [7:0] A,
	input wire [7:0] B,
	input wire [3:0] op,	//功能码，选择运算类型(预留4位，实际1位就行)
	output wire [7:0] E,
	output wire [1:0] cc	//编码两个操作数，左边用于标识AB是否相等，相等的话为1.
							//右边用于标识A是否大于B，1表示A大于B，0表示A小于B

);
	assign E = ( op == 4'h0 )? A+B :
		   		(op == 4'h1) ? A-B : 8'hxx;
		   		
	assign cc =  {A==B,A>B} 	;  //拼接运算符

endmodule

//OP=0000 加法 A+B
//OP=0001 减法 A-B
//否则：不定值，以后扩充运算符

REGFILE.v
module REGFILE(
	input wire [2:0] srcA,
	input wire [2:0] srcB,
	output wire [7:0] A,
	output wire [7:0] B,
	input wire [2:0] dstM,   //M端口要写到哪个寄存器的地址
	input wire [2:0] dstE,   //E端口要写到哪个寄存器的地址
	input wire [7:0] M,			
	input wire [7:0] E,
	input wire clk	
);

	reg [7:0] rf [0:7];

//读电路：
	assign A = (srcA==3'b000)? 8'h00 : rf[srcA];  //如果srcA是0必须返回一个零值(寄存器的地址是R0的地址，取出一个0值)
	assign B = (srcB==3'o0)? 8'h00 : rf[srcB]; //同上
	
//写操作：
	always @(posedge clk) 
    begin
		if(dstM!=3'o0) //寄存器地址不能为0(不能往R0里面写)
            rf[dstM] <= M;					
		if(dstE!=3'o0 && dstE!=dstM)  //如果两个地址是同一个地址，需要有一个优先级(POP指令会涉及)，令M端口优先(栈顶的值存入EXP中)
            rf[dstE] <= E;		
	end
endmodule

PC.v
//用于给出指令在指令储存器中的地址
//在时钟信号的上升沿更新，而且需要一个控制信号，在控制信号为0的时候初始化PC寄存器
module PC(
	input wire [7:0] new_pc,  //目标地址，可能是跳转地址或者是下一条指令的地址
	output reg [7:0] pc, //指令地址，输出信号
	input wire clk,  //时钟周期
	input wire rst_  
);
	always @(posedge clk or negedge rst_) 
	begin
		if(rst_==1'b0)
			begin
			pc<=0;
			end
	 	else    //返回指令地址
			begin
			pc<=new_pc;
			end
	end
		
endmodule

TINYCPU.v
`include "tinyCPU.h"

`define ins rom_data[23:20]   	// -> icode (ROM中高四位)
`define fun rom_data[19:16]		// -> ifun (ROM中低四位)，功能码，不需要的地方功能码为0
`define rA  rom_data[14:12]		//只用3位来表示Ra（一共8个寄存器，3位寻址）
`define rB  rom_data[10:8]    //只用3位
`define rC 	rom_data[6:4]		//第三个字节高四位的低三位用来表示rC

module TINYCPU(
	//连接RAM端口
	output wire [7:0] ram_addr,  //写RAM地址
	output wire [7:0] ram_wdat,  //向RAM写数据总线
	input wire [7:0] ram_rdat,  //读总线
	output wire ram_rd_,ram_wr_,  //控制信号
	
	//连接ROM端口
	output wire [7:0] rom_addr,
	input wire [23:0] rom_data,
	
	//时钟信号与复位信号(CPU复位->PC寄存器置0，从0取出第一条地址)
	input wire clk,rst_
);

	wire [7:0] valA,valB,valC,valP,valE,valM,aluA,aluB,new_pc;
	wire [1:0] cc;
	wire [2:0] dstE, dstM;
	wire [2:0] val_rA, val_rB;
//取指阶段	
	PC pc( .new_pc(new_pc),.pc(rom_addr),.clk(clk),.rst_(rst_)); //实例化一个PC寄存器

	//valC在其他指令中是第三个字节，在JMP中是第二个字节:
	assign valC = ((`ins==`JXX && `fun==`JMP)||`ins==`CALL)? rom_data[15:8]: rom_data[7:0];  //如果取出来了一个无条件转移指令，输出第二个字节，否则其他的是第三个字节
	//指令大部分为3字节指令,HLT和NOP是单字节，JMP是2字节。HLT为停机指令，不再增加。
	assign valP = rom_addr + ((`ins==`HLT )? 0:
						 (`ins==`NOP||`ins==`RET)? 1: 
						 ((`ins==`JXX && `fun==`JMP)||`ins==`CALL)? 2: 3);  //下一条指令的地址
//译码阶段(从REGFILE中读操作数rA,rB，读出来的值传到valA和valB中)
	assign val_rA = (`ins==`POP)? `rB:
					(`ins==`RET)? 3'o7: `rA;
	assign val_rB = (`ins==`CALL||`ins==`RET)? 3'o7: `rB;
	
	//当`ins==`CALL时，regfile读出寄存器Ra的值赋值给valA,读出寄存器7的值赋值给valB
	//当`ins==`RET时，regfile读出寄存器7的值赋值给valA和valB
	//当`ins==`PUSH时，regfile读出寄存器Ra(操作数，存放进栈数据)的值赋值给valA,读出Rb(当前的栈顶指针)的值赋值给valB
	//当`ins==`POP时，regfile读出寄存器Rb(当前的栈顶指针)的值赋值给valA和valB

	REGFILE regfile(.srcA(val_rA),.srcB(val_rB),.A(valA),.B(valB),.dstM(dstM),.dstE(dstE),.M(valM),.E(valE),.clk(clk)	);  
	//实例化译码器，虽然全部读出来了但是不一定都用(比如JMP就不用rB；比如LD中虽然有rA,rB，但是rB不是源操作数，应该是读出来的值应该写入的内存地址，即destM)，这样可以简化电路
	//源操作数：用rA来选择A寄存器，rB来选择B寄存器
	//输出：A端口输出的信号为valA，B端口输出的信号为valB

//执行阶段
	assign aluA = (`ins==`PUSH||`ins==`POP||`ins==`CALL||`ins==`RET)? valB:valA;
	//如果是堆栈操作相关，传递进去栈顶指针
	assign aluB = (`ins==`LD||`ins==`ST||`ins==`OPI)? valC: 
				  (`ins==`PUSH||`ins==`POP||`ins==`CALL||`ins==`RET)? 8'b00000001: valB;	//第二个操作数为常数(不为valB)的情况传入valC
	//如果为堆栈指令，执行栈顶指针加减1操作，如果是进栈fun为1，执行减一，否则加一
	ALU alu(.A(aluA),.B(aluB),.op(`fun),.E(valE),.cc(cc));   //实例化一个运算器
	//错误的代码(比如转移指令)也会使用ALU并计算出一个错误的结果，但是不会使用到，只有运算指令才会使用到ALU的结果
//访存阶段(读写RAM):
	//只有LD和ST指令需要访存
	assign ram_addr=(`ins==`POP||`ins==`RET)? valA: valE; //地址就是运算器输出的结果	
	assign valM=ram_rdat ;  //从RAM读出来的值写到valM端口
	assign ram_rd_ = (`ins==`LD||`ins==`POP||`ins==`RET)? 1'b0: 1'b1;			//读控信号，LD命令，rd_信号有效
	assign ram_wr_ = (`ins==`ST||`ins==`PUSH||`ins==`CALL)? 1'b0: 1'b1;				//写控信号，ST命令，wr_信号有效 
//写回阶段:
	assign ram_wdat= (`ins==`PUSH)? valA:
					 (`ins==`CALL)? valP: valB;  //如果是写指令(ST)
	assign dstM = (`ins==`LD) ? `rB : 
				  (`ins==`POP)? `rA : 3'o0; //代替写使能信号，不是LD的话全写0，表示不写入寄存器
	assign dstE = (`ins==`OPR)? `rC :
				  (`ins==`OPI) ? `rB :
				  (`ins==`PUSH||`ins==`POP)? `rB:
				  (`ins==`CALL||`ins==`RET)? 3'b111: 3'o0;
				  //其他指令不应该修改寄存器内容		  
//更新PC阶段：
	assign new_pc= (
					(`ins==`CALL)||
					(`ins == `JXX && `fun == `JMP)||
					(`ins == `JXX && `fun == `BEQ &&  cc[1:1])||
					(`ins == `JXX && `fun == `BNE && ~cc[1:1])||
					(`ins == `JXX && `fun == `BLT && ~cc[1:1] && ~cc[0:0])||
					(`ins == `JXX && `fun == `BGT && ~cc[1:1] &&  cc[0:0]))? valC :
					(`ins==`RET)? valM:valP;
					//如果成功转移则为valC,不转移则为下一条指令valP
			
endmodule

ROM.v
module ROM(
	input wire [7:0] addr,   //8位地址输入
	output wire [23 :0] out   //需要输出一整条指令，需要三个字节24位
);

	reg [7:0] mem [0:255];  //存储单元
	
	assign out = {mem[addr],mem[addr+1],mem[addr+2]};   //连续输出三个字节
	
	initial
		$readmemh("rom.txt",mem,0,255); //利用系统任务读入
	
endmodule

RAM.v
module RAM(
	input wire [7:0] addr,   //地址总线
	input wire [7:0] in,  //数据总线
	output wire [7:0] out,   //数据输出
	input wire rd_, //控制读信号(低电平有效)
	input wire wr_, //控制写信号(低电平有效)
	input wire clk
);
	reg [7:0] mem [0:255];   //存储单元，共256个，每一个8位
		
	assign out = (rd_==1'b0)? mem[addr] : 8'hxx;	//读数据

	always @(posedge clk) 
		if(wr_==1'b0)  //写信号有效时写入数据
			mem[addr] <= in;  //线网型尽可能连续赋值

endmodule

test.v
`timescale 10ns/1ns

`include "tinyCPU.h"

`define ins rom_out [23:20]

module test;
	wire [7:0] ram_addr, ram_in ,ram_out, rom_addr;
	wire [23:0] rom_out;
	wire rd_,wr_;
	reg clk,rst_;
	
	parameter CYCLE =1.0;
	
	RAM ram(.addr(ram_addr),.in(ram_in),.out(ram_out),.rd_(rd_),.wr_(wr_),.clk(clk));
	ROM rom(.addr(rom_addr),.out(rom_out));
	
	TINYCPU cpu (.ram_addr(ram_addr),.ram_wdat(ram_in),.ram_rdat(ram_out),.ram_rd_(rd_),.ram_wr_(wr_),
				.rom_addr(rom_addr),.rom_data(rom_out),
				.clk(clk),.rst_(rst_));
				
	always #(CYCLE/2)  clk <= ~clk;  //产生时钟
	
	integer i;

	//每到时钟的下降沿(时钟周期的中间时刻)，把内存中前32位的值输出一遍:
	always @(negedge clk) begin
		if (rst_&&(`ins==`HLT)) #(CYCLE+0.1) $finish; //结束当前仿真
		$write("%3d: ",$stime); //显示出仿真时间
		//for(i=0;i<32;i=i+1)
		//	if(ram.mem[i]!==8'hxx) $write(" %c ",ram.mem[i]); 
		//	else $write(" .  ");  //如果是不确定值，输出一个·
		for(i=0;i<=7;i=i+1)
			if(cpu.regfile.rf[i]!==8'hxx) $write(" %d ",cpu.regfile.rf[i]); 
			else $write(" .  ");  //如果是不确定值，输出一个·
		$write("\n"); 
		end
	
	initial begin    
		$dumpfile("test.vcd");
		$dumpvars;
		cpu.regfile.rf[0] = 0;
		cpu.regfile.rf[1] = 1;
		cpu.regfile.rf[2] = 2;
		cpu.regfile.rf[3] = 3;
		cpu.regfile.rf[4] = 4;
		cpu.regfile.rf[5] = 5;
		cpu.regfile.rf[6] = 6;
		cpu.regfile.rf[7] = 8'b11111111;
		$readmemh("ram.txt",ram.mem,0,255);   //16进制
		$readmemh("rom.txt",rom.mem,0,255);   //16进制
		clk=1'b1; 
		rst_=1'b0; #(CYCLE+CYCLE/2) rst_= ~rst_;  //初始reset为0，一个半时钟周期后reset结束
		end

endmodule

test.vcd
$date
	Tue Jun 22 09:18:49 2021
$end
$version
	Icarus Verilog
$end
$timescale
	1ns
$end
$scope module test $end
$var wire 1 ! wr_ $end
$var wire 24 " rom_out [23:0] $end
$var wire 8 # rom_addr [7:0] $end
$var wire 1 $ rd_ $end
$var wire 8 % ram_out [7:0] $end
$var wire 8 & ram_in [7:0] $end
$var wire 8 ' ram_addr [7:0] $end
$var reg 1 ( clk $end
$var reg 1 ) rst_ $end
$var integer 32 * i [31:0] $end
$scope module cpu $end
$var wire 1 ( clk $end
$var wire 1 ) rst_ $end
$var wire 8 + valM [7:0] $end
$var wire 3 , val_rB [2:0] $end
$var wire 3 - val_rA [2:0] $end
$var wire 8 . valP [7:0] $end
$var wire 8 / valE [7:0] $end
$var wire 8 0 valC [7:0] $end
$var wire 8 1 valB [7:0] $end
$var wire 8 2 valA [7:0] $end
$var wire 24 3 rom_data [23:0] $end
$var wire 8 4 rom_addr [7:0] $end
$var wire 1 ! ram_wr_ $end
$var wire 8 5 ram_wdat [7:0] $end
$var wire 8 6 ram_rdat [7:0] $end
$var wire 1 $ ram_rd_ $end
$var wire 8 7 ram_addr [7:0] $end
$var wire 8 8 new_pc [7:0] $end
$var wire 3 9 dstM [2:0] $end
$var wire 3 : dstE [2:0] $end
$var wire 2 ; cc [1:0] $end
$var wire 8 < aluB [7:0] $end
$var wire 8 = aluA [7:0] $end
$scope module alu $end
$var wire 8 > A [7:0] $end
$var wire 8 ? B [7:0] $end
$var wire 4 @ op [3:0] $end
$var wire 2 A cc [1:0] $end
$var wire 8 B E [7:0] $end
$upscope $end
$scope module pc $end
$var wire 1 ( clk $end
$var wire 8 C new_pc [7:0] $end
$var wire 1 ) rst_ $end
$var reg 8 D pc [7:0] $end
$upscope $end
$scope module regfile $end
$var wire 8 E E [7:0] $end
$var wire 8 F M [7:0] $end
$var wire 1 ( clk $end
$var wire 3 G dstE [2:0] $end
$var wire 3 H dstM [2:0] $end
$var wire 3 I srcA [2:0] $end
$var wire 3 J srcB [2:0] $end
$var wire 8 K B [7:0] $end
$var wire 8 L A [7:0] $end
$upscope $end
$upscope $end
$scope module ram $end
$var wire 8 M addr [7:0] $end
$var wire 1 ( clk $end
$var wire 8 N in [7:0] $end
$var wire 1 $ rd_ $end
$var wire 1 ! wr_ $end
$var wire 8 O out [7:0] $end
$upscope $end
$scope module rom $end
$var wire 8 P addr [7:0] $end
$var wire 24 Q out [23:0] $end
$upscope $end
$upscope $end
$enddefinitions $end
#0
$dumpvars
b0 Q
b0 P
bx O
b0 N
b0 M
b0 L
b0 K
b0 J
b0 I
b0 H
b0 G
bx F
b0 E
b0 D
b1 C
b0 B
b10 A
b0 @
b0 ?
b0 >
b0 =
b0 <
b10 ;
b0 :
b0 9
b1 8
b0 7
bx 6
b0 5
b0 4
b0 3
b0 2
b0 1
b0 0
b0 /
b1 .
b0 -
b0 ,
bx +
bx *
0)
1(
b0 '
b0 &
bx %
1$
b0 #
b0 "
1!
$end
#5
b1000 *
0(
#10
1(
#15
b1000 *
0(
1)
#20
b10 8
b10 C
b10 .
b1 #
b1 4
b1 D
b1 P
1(
#25
b1000 *
0(
#30
b11 8
b11 C
b11 .
b10 #
b10 4
b10 D
b10 P
1(
#35
b1000 *
0(
#40
b1100001 0
b100 8
b100 C
b1100001 "
b1100001 3
b1100001 Q
b100 .
b11 #
b11 4
b11 D
b11 P
1(
#45
b1000 *
0(
#50
b111 '
b111 7
b111 M
b111 /
b111 B
b111 E
b1 &
b1 5
b1 N
b1 <
b1 ?
b1 ;
b1 A
b110 =
b110 >
b110 2
b110 L
b1 1
b1 K
b110 -
b110 I
b1 ,
b1 J
b110111 0
b101 8
b101 C
b110000100110111 "
b110000100110111 3
b110000100110111 Q
b101 .
b100 #
b100 4
b100 D
b100 P
1(
#55
b1000 *
0(
#60
b111 :
b111 G
b1 ;
b1 A
b1 <
b1 ?
b11111111 =
b11111111 >
0!
b11 2
b11 L
b11111110 '
b11111110 7
b11111110 M
b11111111 1
b11111111 K
b11 -
b11 I
b11 &
b11 5
b11 N
b11111110 /
b11111110 B
b11111110 E
b111 ,
b111 J
b0 0
b1000 8
b1000 C
b1 @
b11000010011011100000000 "
b11000010011011100000000 3
b11000010011011100000000 Q
b1000 .
b101 #
b101 4
b101 D
b101 P
1(
#65
b1000 *
0(
#70
1!
b11 :
b11 G
b100 '
b100 7
b100 M
b11 &
b11 5
b11 N
b100 /
b100 B
b100 E
b11 ,
b11 J
b1 0
b1011 8
b1011 C
b11 =
b11 >
b0 @
b11 1
b11 K
b10000000011001100000001 "
b10000000011001100000001 3
b10000000011001100000001 Q
b1011 .
b1000 #
b1000 4
b1000 D
b1000 P
1(
#75
b1000 *
0(
#80
b11 +
b11 F
b11 %
b11 6
b11 O
0$
b10 9
b10 H
b11111110 '
b11111110 7
b11111110 M
b111 :
b111 G
b1 ;
b1 A
b1 <
b1 ?
b11111111 /
b11111111 B
b11111111 E
b11111110 &
b11111110 5
b11111110 N
b111 -
b111 I
b111 ,
b111 J
b0 0
b1110 8
b1110 C
b11111110 =
b11111110 >
b11111110 2
b11111110 L
b11111110 1
b11111110 K
b11100000010011100000000 "
b11100000010011100000000 3
b11100000010011100000000 Q
b1110 .
b1011 #
b1011 4
b1011 D
b1011 P
1(
#85
b1000 *
0(
#90
b0 <
b0 ?
1$
b0 :
b0 G
b10 ;
b10 A
b0 9
b0 H
bx +
bx F
bx %
bx 6
bx O
b0 &
b0 5
b0 N
b0 /
b0 B
b0 E
b0 ,
b0 J
b0 -
b0 I
b1111 8
b1111 C
b0 '
b0 7
b0 M
b0 =
b0 >
b0 2
b0 L
b0 1
b0 K
b0 "
b0 3
b0 Q
b1111 .
b1110 #
b1110 4
b1110 D
b1110 P
1(
#95
b1000 *
0(
#100
b10000 8
b10000 C
b10000 .
b1111 #
b1111 4
b1111 D
b1111 P
1(
#105
b1000 *
0(
#110
b10001 8
b10001 C
b10001 .
b10000 #
b10000 4
b10000 D
b10000 P
1(
#115
b1000 *
0(
#120
b11110000 0
b10010 8
b10010 C
b11110000 "
b11110000 3
b11110000 Q
b10010 .
b10001 #
b10001 4
b10001 D
b10001 P
1(
#125
b1000 *
0(
#130
b11111111 '
b11111111 7
b11111111 M
b11111111 /
b11111111 B
b11111111 E
b1 ;
b1 A
b11111111 =
b11111111 >
b11111111 2
b11111111 L
b111 -
b111 I
bx 0
b10011 8
b10011 C
b11110000xxxxxxxx "
b11110000xxxxxxxx 3
b11110000xxxxxxxx Q
b10011 .
b10010 #
b10010 4
b10010 D
b10010 P
1(
#135
b1000 *
0(
#140
bx '
bx 7
bx M
bx /
bx B
bx E
bx &
bx 5
bx N
bx <
bx ?
bx ;
bx A
bx =
bx >
bx 2
bx L
bx 1
bx K
bx -
bx I
bx ,
bx J
b10011 8
b10011 C
b11110000xxxxxxxxxxxxxxxx "
b11110000xxxxxxxxxxxxxxxx 3
b11110000xxxxxxxxxxxxxxxx Q
b10011 .
b10011 #
b10011 4
b10011 D
b10011 P
1(
